cfgtree/__init__.py
cfgtree/dictxpath.py
cfgtree/cmdline_parsers/__init__.py
cfgtree/cmdline_parsers/argparse.py
cfgtree/cmdline_parsers/dummy.py
cfgtree/models/__init__.py
cfgtree/models/anyconfig.py
cfgtree/storages/__init__.py
cfgtree/storages/_base.py
cfgtree/storages/_single_file.py
cfgtree/storages/anyconfig.py
cfgtree/storages/json.py
cfgtree/storages/tests/__init__.py
cfgtree/storages/tests/_common.py
cfgtree/storages/tests/test_anyconfig.py
cfgtree/storages/tests/test_json_storage.py
cfgtree/storages/tests/test_yaml_storage.py
cfgtree/tests/__init__.py
cfgtree/tests/test_dictxpath.py
cfgtree/types/__init__.py
cfgtree-1.1.1.dist-info/DESCRIPTION.rst
cfgtree-1.1.1.dist-info/LICENSE.txt
cfgtree-1.1.1.dist-info/METADATA
cfgtree-1.1.1.dist-info/RECORD
cfgtree-1.1.1.dist-info/WHEEL
cfgtree-1.1.1.dist-info/metadata.json
cfgtree-1.1.1.dist-info/pbr.json
cfgtree-1.1.1.dist-info/top_level.txt
