Metadata-Version: 2.0
Name: cfgtree
Version: 1.1.1
Summary: Automatic configuration file, command line, environment variable parser
Home-page: https://github.com/gsemet/cfgtree
Author: Gaetan Semet
Author-email: gaetan@xeberon.net
License: UNKNOWN
Platform: UNKNOWN
Classifier: Intended Audience :: Information Technology
Classifier: Intended Audience :: System Administrators
Classifier: License :: OSI Approved :: MIT License
Classifier: Operating System :: POSIX :: Linux
Classifier: Programming Language :: Python
Classifier: Programming Language :: Python :: 3
Classifier: Programming Language :: Python :: 3.5
Classifier: Programming Language :: Python :: 3.6
Requires-Dist: anyconfig
Requires-Dist: jsonschema
Requires-Dist: pbr (>=3.0)
